oncore/__init__.py
oncore/matcher.py
oncore/test_matcher.py
oncore-0.0.1.dist-info/LICENSE
oncore-0.0.1.dist-info/METADATA
oncore-0.0.1.dist-info/WHEEL
oncore-0.0.1.dist-info/top_level.txt
oncore-0.0.1.dist-info/RECORD
